Metadata-Version: 1.0
Name: super-hiper-hello
Version: 0.0.1
Summary: HELLO DESCRIPTION FTW!
Home-page: UNKNOWN
Author: UNKNOWN
Author-email: UNKNOWN
License: UNKNOWN
Platform: UNKNOWN
